bumbo/__init__.py
bumbo/api.py
bumbo/middleware.py
bumbo/orm.py
bumbo/response.py
marcosgeo_bumbo-0.0.7.dist-info/METADATA
marcosgeo_bumbo-0.0.7.dist-info/WHEEL
marcosgeo_bumbo-0.0.7.dist-info/top_level.txt
marcosgeo_bumbo-0.0.7.dist-info/RECORD
