Metadata-Version: 2.1
Name: marcosgeo-bumbo
Version: 0.0.7
Summary: Bumbo Python Web Framework built for learning purposes.
Home-page: UNKNOWN
Author: Antonio Marcos
Author-email: marcosgeo@yahoo.com
License: MIT
Platform: UNKNOWN
Classifier: Programming Language :: Python :: 3.6
Requires-Python: >=3.6.0
Requires-Dist: Jinja2 (==3.1.2)
Requires-Dist: WebOb (==1.8.5)
Requires-Dist: parse (==1.19.0)
Requires-Dist: requests-wsgi-adapter (==0.4.1)
Requires-Dist: requests (==2.22.0)
Requires-Dist: whitenoise (==4.1.4)
